sqlty/__init__.py
sqlty/__main__.py
sqlty/_ast_builder.py
sqlty/_ast_unparser.py
sqlty/_auto_generator.py
sqlty/_collector.py
sqlty/_config.py
sqlty/_generator.py
sqlty/_registry.py
sqlty/_sql_analyzer.py
sqlty/_stub_merger.py
sqlty/py.typed
sqlty/drivers/psycopg.py
sqlty-0.0.1.dev1.dist-info/METADATA
sqlty-0.0.1.dev1.dist-info/WHEEL
sqlty-0.0.1.dev1.dist-info/entry_points.txt
sqlty-0.0.1.dev1.dist-info/licenses/LICENSE
sqlty-0.0.1.dev1.dist-info/RECORD
