Metadata-Version: 2.4
Name: sqlty
Version: 0.0.1.dev1
Summary: Type-safe SQL queries for Python with automatic stub generation
Project-URL: Homepage, https://github.com/jirikuncar/sqlty
Project-URL: Documentation, https://github.com/jirikuncar/sqlty#readme
Project-URL: Repository, https://github.com/jirikuncar/sqlty
Project-URL: Changelog, https://github.com/jirikuncar/sqlty/releases
Project-URL: Issues, https://github.com/jirikuncar/sqlty/issues
Author-email: Jiri Kuncar <jiri.kuncar@gmail.com>
License: MIT License
License-File: LICENSE
Keywords: code-generation,mypy,sql,static-analysis,stub-files,type-hints,type-safety
Classifier: Development Status :: 3 - Alpha
Classifier: Intended Audience :: Developers
Classifier: License :: OSI Approved :: MIT License
Classifier: Programming Language :: Python :: 3
Classifier: Programming Language :: Python :: 3.14
Classifier: Programming Language :: SQL
Classifier: Topic :: Database
Classifier: Topic :: Software Development :: Code Generators
Classifier: Topic :: Software Development :: Libraries :: Python Modules
Classifier: Typing :: Typed
Requires-Python: >=3.14
Requires-Dist: sqlglot>=27.29.0
Provides-Extra: psycopg
Requires-Dist: psycopg>=3.2.12; extra == 'psycopg'
